necroassembler/__init__.py
necroassembler/assembler.py
necroassembler/exceptions.py
necroassembler/macros.py
necroassembler/statements.py
necroassembler/tokenizer.py
necroassembler/utils.py
necroassembler/cpu/intel8086.py
necroassembler/cpu/lr35902.py
necroassembler/cpu/mc68000.py
necroassembler/cpu/mips32.py
necroassembler/cpu/mos6502.py
necroassembler/cpu/powerpc.py
necroassembler/cpu/thumb.py
necroassembler/cpu/z80.py
necroassembler/platforms/gameboy.py
necroassembler/platforms/gba.py
necroassembler/platforms/genesis.py
necroassembler/platforms/mz.py
necroassembler/platforms/nes.py
necroassembler/platforms/psx.py
necroassembler/platforms/sms.py
necroassembler-0.8.dist-info/LICENSE
necroassembler-0.8.dist-info/METADATA
necroassembler-0.8.dist-info/WHEEL
necroassembler-0.8.dist-info/entry_points.txt
necroassembler-0.8.dist-info/top_level.txt
necroassembler-0.8.dist-info/zip-safe
necroassembler-0.8.dist-info/RECORD
