Metadata-Version: 2.1
Name: necroassembler
Version: 0.8
Summary: framework for building assemblers
Home-page: https://github.com/rdeioris/necroassembler/
Author: Roberto De Ioris
Author-email: roberto.deioris@gmail.com
License: MIT
Platform: UNKNOWN
